{
  "updateTeamsMeta": "2025-04-18T16:26:52.141Z",
  "updateCurrentMonthMatch": "2025-05-10T11:40:39.302Z",
  "fetchLineups": "2025-05-01T00:56:32.616Z",
  "fetchScores": "2025-05-10T11:40:34.977Z",
  "updateMatchdayStatus": "2025-05-10T05:18:43.190Z",
  "updateJleagueSchedule": "2025-05-09T22:10:30.667Z",
  "updateCelticSchedule": "2025-05-09T22:16:39.538Z",
  "updatePlayers": "2025-04-15T06:20:28.888Z",
  "mergeMatches": "2025-05-09T22:02:05.085Z",
  "updateSeason": "2025-05-09T22:20:05.447Z"
}