{
  "updateTeamsMeta": "2025-04-18T16:26:52.141Z",
  "updateCurrentMonthMatch": "2025-05-23T12:52:36.464Z",
  "fetchLineups": "2025-05-01T00:56:32.616Z",
  "fetchScores": "2025-05-23T12:52:32.136Z",
  "updateMatchdayStatus": "2025-05-23T05:20:11.744Z",
  "updateJleagueSchedule": "2025-05-22T22:11:07.021Z",
  "updateCelticSchedule": "2025-05-22T22:16:59.009Z",
  "updatePlayers": "2025-04-15T06:20:28.888Z",
  "mergeMatches": "2025-05-22T22:02:03.829Z",
  "updateSeason": "2025-05-22T22:20:50.930Z"
}