{
  "updateTeamsMeta": "2025-04-18T16:26:52.141Z",
  "updateCurrentMonthMatch": "2025-07-19T22:02:01.583Z",
  "fetchLineups": "2025-07-01T01:00:42.949Z",
  "fetchScores": "2025-07-19T21:44:12.822Z",
  "updateMatchdayStatus": "2025-07-19T05:23:00.037Z",
  "updateJleagueSchedule": "2025-07-19T22:11:20.977Z",
  "updateCelticSchedule": "2025-07-19T22:01:55.838Z",
  "updatePlayers": "2025-07-19T03:52:11.930Z",
  "mergeMatches": "2025-07-19T22:02:04.488Z",
  "updateSeason": "2025-07-18T22:23:00.417Z"
}