{
  "updateTeamsMeta": "2025-04-18T16:26:52.141Z",
  "updateCurrentMonthMatch": "2025-07-05T18:33:54.488Z",
  "fetchLineups": "2025-07-01T01:00:42.949Z",
  "fetchScores": "2025-07-05T18:33:50.729Z",
  "updateMatchdayStatus": "2025-07-05T05:20:28.123Z",
  "updateJleagueSchedule": "2025-07-04T22:11:16.019Z",
  "updateCelticSchedule": "2025-07-04T22:17:23.350Z",
  "updatePlayers": "2025-07-05T03:45:06.779Z",
  "mergeMatches": "2025-07-04T22:08:56.304Z",
  "updateSeason": "2025-07-04T22:21:29.584Z"
}