{
  "updateTeamsMeta": "2025-08-01T04:12:46.059Z",
  "updateCurrentMonthMatch": "2025-09-16T22:39:12.455Z",
  "fetchLineups": "2025-09-01T00:59:31.168Z",
  "fetchScores": "2025-09-16T22:39:08.168Z",
  "updateMatchdayStatus": "2025-09-16T05:18:52.987Z",
  "updateJleagueSchedule": "2025-09-16T22:10:17.563Z",
  "updateCelticSchedule": "2025-09-16T22:02:06.058Z",
  "updatePlayers": "2025-09-16T03:29:21.556Z",
  "mergeMatches": "2025-09-16T22:02:13.782Z",
  "updateSeason": "2025-09-16T22:18:48.298Z"
}