{
  "updateTeamsMeta": "2025-08-01T04:12:46.059Z",
  "updateCurrentMonthMatch": "2025-08-10T14:24:46.568Z",
  "fetchLineups": "2025-08-01T01:04:30.556Z",
  "fetchScores": "2025-08-10T14:24:42.729Z",
  "updateMatchdayStatus": "2025-08-10T05:24:53.568Z",
  "updateJleagueSchedule": "2025-08-09T22:11:06.095Z",
  "updateCelticSchedule": "2025-08-09T22:17:36.667Z",
  "updatePlayers": "2025-08-10T04:04:07.614Z",
  "mergeMatches": "2025-08-09T22:08:38.888Z",
  "updateSeason": "2025-08-09T22:21:46.875Z"
}