{
  "updateTeamsMeta": "2025-08-01T04:12:46.059Z",
  "updateCurrentMonthMatch": "2025-09-09T07:41:54.214Z",
  "fetchLineups": "2025-09-01T00:59:31.168Z",
  "fetchScores": "2025-09-09T07:41:50.397Z",
  "updateMatchdayStatus": "2025-09-09T05:19:27.228Z",
  "updateJleagueSchedule": "2025-09-08T22:10:48.489Z",
  "updateCelticSchedule": "2025-09-08T22:16:14.176Z",
  "updatePlayers": "2025-09-09T03:33:26.408Z",
  "mergeMatches": "2025-09-08T22:02:23.923Z",
  "updateSeason": "2025-09-08T22:19:42.155Z"
}