{
  "updateTeamsMeta": "2025-08-01T04:12:46.059Z",
  "updateCurrentMonthMatch": "2026-01-14T04:53:19.128Z",
  "fetchLineups": "2026-01-01T01:02:43.179Z",
  "fetchScores": "2026-01-14T04:53:15.064Z",
  "updateMatchdayStatus": "2026-01-14T05:26:38.382Z",
  "updateJleagueSchedule": "2026-01-13T22:13:10.407Z",
  "updateCelticSchedule": "2026-01-13T22:20:45.136Z",
  "updatePlayers": "2026-01-14T04:04:56.599Z",
  "mergeMatches": "2026-01-13T22:02:15.955Z",
  "updateSeason": "2026-01-13T22:25:54.198Z"
}