{
  "updateTeamsMeta": "2025-08-01T04:12:46.059Z",
  "updateCurrentMonthMatch": "2025-09-05T12:50:30.954Z",
  "fetchLineups": "2025-09-01T00:59:31.168Z",
  "fetchScores": "2025-09-05T12:50:26.884Z",
  "updateMatchdayStatus": "2025-09-05T05:19:07.817Z",
  "updateJleagueSchedule": "2025-09-04T22:10:36.860Z",
  "updateCelticSchedule": "2025-09-04T22:15:56.206Z",
  "updatePlayers": "2025-09-05T03:30:35.570Z",
  "mergeMatches": "2025-09-04T22:01:56.026Z",
  "updateSeason": "2025-09-04T22:19:25.060Z"
}